setup.py
pypool/__init__.py
pypool.egg-info/PKG-INFO
pypool.egg-info/SOURCES.txt
pypool.egg-info/dependency_links.txt
pypool.egg-info/not-zip-safe
pypool.egg-info/top_level.txt