Metadata-Version: 1.0
Name: pypool
Version: 0.1
Summary: Connection pooling library
Home-page: http://github.com/babbarshaer/pypool
Author: Abhimanyu Babbar
Author-email: abhimanyu.babbar89@gmail.com
License: Apache License v2.0
Platform: UNKNOWN
